devolo_plc_api/__init__.py
devolo_plc_api/device.py
devolo_plc_api/py.typed
devolo_plc_api/clients/__init__.py
devolo_plc_api/clients/protobuf.py
devolo_plc_api/device_api/__init__.py
devolo_plc_api/device_api/deviceapi.py
devolo_plc_api/device_api/deviceapi.pyi
devolo_plc_api/device_api/factoryreset_pb2.py
devolo_plc_api/device_api/factoryreset_pb2.pyi
devolo_plc_api/device_api/ledsettings_pb2.py
devolo_plc_api/device_api/ledsettings_pb2.pyi
devolo_plc_api/device_api/multiap_pb2.py
devolo_plc_api/device_api/multiap_pb2.pyi
devolo_plc_api/device_api/restart_pb2.py
devolo_plc_api/device_api/restart_pb2.pyi
devolo_plc_api/device_api/support_pb2.py
devolo_plc_api/device_api/support_pb2.pyi
devolo_plc_api/device_api/updatefirmware_pb2.py
devolo_plc_api/device_api/updatefirmware_pb2.pyi
devolo_plc_api/device_api/wifinetwork_pb2.py
devolo_plc_api/device_api/wifinetwork_pb2.pyi
devolo_plc_api/exceptions/__init__.py
devolo_plc_api/exceptions/device.py
devolo_plc_api/exceptions/feature.py
devolo_plc_api/helpers/__init__.py
devolo_plc_api/network/__init__.py
devolo_plc_api/plcnet_api/__init__.py
devolo_plc_api/plcnet_api/getnetworkoverview_pb2.py
devolo_plc_api/plcnet_api/getnetworkoverview_pb2.pyi
devolo_plc_api/plcnet_api/identifydevice_pb2.py
devolo_plc_api/plcnet_api/identifydevice_pb2.pyi
devolo_plc_api/plcnet_api/pairdevice_pb2.py
devolo_plc_api/plcnet_api/pairdevice_pb2.pyi
devolo_plc_api/plcnet_api/plcnetapi.py
devolo_plc_api/plcnet_api/plcnetapi.pyi
devolo_plc_api/plcnet_api/setuserdevicename_pb2.py
devolo_plc_api/plcnet_api/setuserdevicename_pb2.pyi
devolo_plc_api/zeroconf/__init__.py
devolo_plc_api-1.5.0.dist-info/licenses/LICENSE
devolo_plc_api-1.5.0.dist-info/METADATA
devolo_plc_api-1.5.0.dist-info/WHEEL
devolo_plc_api-1.5.0.dist-info/top_level.txt
devolo_plc_api-1.5.0.dist-info/RECORD
