Metadata-Version: 2.4
Name: devolo_plc_api
Version: 1.5.0
Summary: devolo PLC devices in Python
Author-email: Markus Bong <m.bong@famabo.de>, Guido Schmitz <guido.schmitz@fedaix.de>
License-Expression: GPL-3.0-or-later
Project-URL: changelog, https://github.com/2Fake/devolo_plc_api/docs/CHANGELOG.md
Project-URL: homepage, https://github.com/2Fake/devolo_plc_api
Classifier: Programming Language :: Python :: 3
Classifier: Operating System :: OS Independent
Requires-Python: >=3.9
License-File: LICENSE
Requires-Dist: ifaddr>=0.1.7
Requires-Dist: httpx>=0.21.0
Requires-Dist: protobuf>=4.22.0
Requires-Dist: segno>=1.5.2
Requires-Dist: tenacity>=9.0.0
Requires-Dist: zeroconf>=0.70.0
Provides-Extra: dev
Requires-Dist: pre-commit; extra == "dev"
Requires-Dist: mypy>=1.8.0; extra == "dev"
Provides-Extra: test
Requires-Dist: pytest; extra == "test"
Requires-Dist: pytest-asyncio; extra == "test"
Requires-Dist: pytest-cov; extra == "test"
Requires-Dist: pytest-httpx>=0.18.0; extra == "test"
Requires-Dist: typing-extensions; extra == "test"
Requires-Dist: syrupy; extra == "test"
Dynamic: license-file
